LICENSE.txt
README.md
setup.cfg
setup.py
discordoauth/__init__.py
discordoauth/client.py
discordoauth/errors.py
discordoauth/http.py
discordoauth/scopes.py
discordoauth/session.py
discordoauth/utils.py
discordoauth.py.egg-info/PKG-INFO
discordoauth.py.egg-info/SOURCES.txt
discordoauth.py.egg-info/dependency_links.txt
discordoauth.py.egg-info/requires.txt
discordoauth.py.egg-info/top_level.txt