Metadata-Version: 2.1
Name: discordoauth.py
Version: 0.1.2
Summary: Easily using discord webhooks in python - asynchronous and synchronous - documented at https://github.com/Coolo22/discordoauth.py/docs/
Home-page: https://github.com/Coolo22/discordoauth.py
Author: Coolo2
Author-email: itsxcoolo2@gmail.com
License: MIT
Download-URL: https://github.com/Coolo22/discordwebhook.py/raw/master/archive/discordoauth.py-0.1.2.tar.gz
Project-URL: Documentation, https://github.com/Coolo22/discordoauth.py/docs
Project-URL: Issue tracker, https://github.com/Coolo22/discordoauth.py/issues
Keywords: discord,oauth2,python,api,asynchronous,synchronous,oauth
Platform: UNKNOWN
Classifier: Development Status :: 5 - Production/Stable
Classifier: Intended Audience :: Developers
Classifier: Topic :: Software Development :: Build Tools
Classifier: License :: OSI Approved :: MIT License
Classifier: Programming Language :: Python :: 3
Classifier: Programming Language :: Python :: 3.6
Classifier: Programming Language :: Python :: 3.7
Classifier: Programming Language :: Python :: 3.8
Classifier: Programming Language :: Python :: 3.9
Classifier: Programming Language :: Python :: 3.10
License-File: LICENSE.txt
